pandora_cloud/__init__.py
pandora_cloud/py.typed
pandora_cloud/server.py
pandora_cloud/flask/static/apple-touch-icon.png
pandora_cloud/flask/static/favicon-16x16.png
pandora_cloud/flask/static/favicon-32x32.png
pandora_cloud/flask/static/manifest.json
pandora_cloud/flask/static/service-worker.js
pandora_cloud/flask/static/_next/static/chunks/012ff928-bcfa62e3ac82441c.js
pandora_cloud/flask/static/_next/static/chunks/1f110208-cda4026aba1898fb.js
pandora_cloud/flask/static/_next/static/chunks/238-882950710bdd3e1e.js
pandora_cloud/flask/static/_next/static/chunks/271.f8fe486a0f5b221c.js
pandora_cloud/flask/static/_next/static/chunks/2802bd5f-15923fb46be55b45.js
pandora_cloud/flask/static/_next/static/chunks/297-e180277ece10e844.js
pandora_cloud/flask/static/_next/static/chunks/412-c00b85b4ef66af2f.js
pandora_cloud/flask/static/_next/static/chunks/435-2b015d294e66ccbc.js
pandora_cloud/flask/static/_next/static/chunks/564-f0043ba04d4fcd3d.js
pandora_cloud/flask/static/_next/static/chunks/68a27ff6-b1db347c50639918.js
pandora_cloud/flask/static/_next/static/chunks/800-a82eb647282afb06.js
pandora_cloud/flask/static/_next/static/chunks/937-36e251f389e9e752.js
pandora_cloud/flask/static/_next/static/chunks/984-1278472924e49180.js
pandora_cloud/flask/static/_next/static/chunks/bd26816a-7ae54dd3357d90b4.js
pandora_cloud/flask/static/_next/static/chunks/framework-e23f030857e925d4.js
pandora_cloud/flask/static/_next/static/chunks/main-0438431c68fbeb27.js
pandora_cloud/flask/static/_next/static/chunks/polyfills-c67a75d1b6f99dc8.js
pandora_cloud/flask/static/_next/static/chunks/webpack-305aad91bdd6a592.js
pandora_cloud/flask/static/_next/static/chunks/pages/admin-810915a9e0227b64.js
pandora_cloud/flask/static/_next/static/chunks/pages/app-573ad0910def0e5d.js
pandora_cloud/flask/static/_next/static/chunks/pages/bypass-979cf95f72688cf4.js
pandora_cloud/flask/static/_next/static/chunks/pages/error-fdab57c4b88e5b1c.js
ChatGPT_Cloud-0.6.6.dist-info/LICENSE
ChatGPT_Cloud-0.6.6.dist-info/METADATA
ChatGPT_Cloud-0.6.6.dist-info/WHEEL
ChatGPT_Cloud-0.6.6.dist-info/top_level.txt
ChatGPT_Cloud-0.6.6.dist-info/RECORD
